mocktrics_exporter/__init__.py
mocktrics_exporter/api.py
mocktrics_exporter/arguments.py
mocktrics_exporter/configuration.py
mocktrics_exporter/dependencies.py
mocktrics_exporter/main.py
mocktrics_exporter/metaMetrics.py
mocktrics_exporter/metricCollection.py
mocktrics_exporter/metrics.py
mocktrics_exporter/persistence.py
mocktrics_exporter/valueModels.py
mocktrics_exporter-0.2.1.dist-info/licenses/LICENSE
mocktrics_exporter-0.2.1.dist-info/METADATA
mocktrics_exporter-0.2.1.dist-info/WHEEL
mocktrics_exporter-0.2.1.dist-info/entry_points.txt
mocktrics_exporter-0.2.1.dist-info/top_level.txt
mocktrics_exporter-0.2.1.dist-info/RECORD
