Metadata-Version: 2.4
Name: mocktrics-exporter
Version: 0.2.1
Summary: A FastAPI-based mock Prometheus exporter with configurable metrics and UI.
Author: mocktrics Exporter Maintainers
License:                                  Apache License
Project-URL: Homepage, https://github.com/mbrunhoej/mocktrics-exporter
Project-URL: Repository, https://github.com/mbrunhoej/mocktrics-exporter
Keywords: prometheus,exporter,mock,fastapi,metrics
Classifier: Programming Language :: Python :: 3
Classifier: Programming Language :: Python :: 3 :: Only
Classifier: License :: OSI Approved :: Apache Software License
Classifier: Operating System :: OS Independent
Classifier: Framework :: FastAPI
Classifier: Topic :: Internet :: WWW/HTTP
Classifier: Topic :: System :: Monitoring
Requires-Python: >=3.9
License-File: LICENSE
Requires-Dist: prometheus_client
Requires-Dist: PyYAML
Requires-Dist: pydantic>=2
Requires-Dist: fastapi
Requires-Dist: uvicorn
Requires-Dist: python-multipart
Dynamic: license-file
